visionmadeeasyplusmanna.py
visionmadeeasyplusmanna-1.dist-info/METADATA
visionmadeeasyplusmanna-1.dist-info/WHEEL
visionmadeeasyplusmanna-1.dist-info/top_level.txt
visionmadeeasyplusmanna-1.dist-info/RECORD
